command_history_wordcloud/__init__.py
command_history_wordcloud/command_history_wordcloud.py
command_history_wordcloud-1.1.1.dist-info/DESCRIPTION.rst
command_history_wordcloud-1.1.1.dist-info/METADATA
command_history_wordcloud-1.1.1.dist-info/RECORD
command_history_wordcloud-1.1.1.dist-info/WHEEL
command_history_wordcloud-1.1.1.dist-info/entry_points.txt
command_history_wordcloud-1.1.1.dist-info/metadata.json
command_history_wordcloud-1.1.1.dist-info/top_level.txt
